README
setup.py
LitleSdkPython.egg-info/PKG-INFO
LitleSdkPython.egg-info/SOURCES.txt
LitleSdkPython.egg-info/dependency_links.txt
LitleSdkPython.egg-info/requires.txt
LitleSdkPython.egg-info/top_level.txt
litleSdkPython/Communications.py
litleSdkPython/Configuration.py
litleSdkPython/__init__.py
litleSdkPython/litleBatchRequest.py
litleSdkPython/litleBatchResponse.py
litleSdkPython/litleOnlineRequest.py
litleSdkPython/litleXmlFields.py
litleSdkPython/responseParser.py